igv_notebook/VERSION
igv_notebook/VERSION_IGV
igv_notebook/__init__.py
igv_notebook/browser.py
igv_notebook/file_reader.py
igv_notebook/svg.py
igv_notebook/version.py
igv_notebook/js/igv.iife.js
igv_notebook/js/igv.min.js
igv_notebook/js/localNotebookFile.js
igv_notebook/js/messageHandler.js
igv_notebook-0.6.2.dist-info/LICENSE.md
igv_notebook-0.6.2.dist-info/METADATA
igv_notebook-0.6.2.dist-info/WHEEL
igv_notebook-0.6.2.dist-info/top_level.txt
igv_notebook-0.6.2.dist-info/RECORD
