Metadata-Version: 2.1
Name: igv-notebook
Version: 0.6.2
Summary: Package for embedding the igv.js genome visualization in IPython notebooks
Home-page: https://github.com/igvteam/igv-notebook
Author: Jim Robinson
License: MIT
Keywords: igv,bioinformatics,genomics,visualization,ipython,jupyter
Platform: UNKNOWN
Classifier: Development Status :: 4 - Beta
Classifier: Intended Audience :: Science/Research
Classifier: Intended Audience :: Developers
Classifier: License :: OSI Approved :: MIT License
Classifier: Programming Language :: Python
Classifier: Framework :: IPython
License-File: LICENSE.md
Requires-Dist: ipykernel
Requires-Dist: ipython
Requires-Dist: requests
